{
  "text_unique": "0.00",
  "unique": "0.00",
  "result_json": {
    "date_check": "24.12.2017 22:18:32",
    "unique": "0",
    "urls": [
      {
        "url": "http://hubs.ua/authority/naval-ny-j-idet-v-prezidenty-120748.html",
        "plagiat": 100,
        "words": "0 1 2 3 4 5 6 7 8 9 10 11 12 13 14 15 16 17 18 19 20 21 22 23 24 25 26 27 28 29 30 31 32"
      },
      {
        "url": "http://kontrakty.ua/article/110595",
        "plagiat": 100,
        "words": "0 1 2 3 4 5 6 7 8 9 10 11 12 13 14 15 16 17 18 19 20 21 22 23 24 25 26 27 28 29 30 31 32"
      },
      {
        "url": "https://korrespondent.net/world/russia/3921800-navalnoho-vydvynuly-v-prezydenty-rossyy",
        "plagiat": 100,
        "words": "0 1 2 3 4 5 6 7 8 9 10 11 12 13 14 15 16 17 18 19 20 21 22 23 24 25 26 27 28 29 30 31 32"
      },
      {
        "url": "http://yenicag.ru/navalnogo-vydvinuli-kandidatom-na-p/",
        "plagiat": 100,
        "words": "0 1 2 3 4 5 6 7 8 9 10 11 12 13 14 15 16 17 18 19 20 21 22 23 24 25 26 27 28 29 30 31 32"
      },
      {
        "url": "https://www.facenews.ua/news/2017/388691/",
        "plagiat": 100,
        "words": "0 1 2 3 4 5 6 7 8 9 10 11 12 13 14 15 16 17 18 19 20 21 22 23 24 25 26 27 28 29 30 31 32"
      },
      {
        "url": "http://thekievtimes.ua/society/531936-navalnyj-dobilsya-svoego.html",
        "plagiat": 100,
        "words": "0 1 2 3 4 5 6 7 8 9 10 11 12 13 14 15 16 17 18 19 20 21 22 23 24 25 26 27 28 29 30 31 32"
      },
      {
        "url": "http://www.pravda.com.ua/rus/news/2017/12/24/7166600/",
        "plagiat": 100,
        "words": "0 1 2 3 4 5 6 7 8 9 10 11 12 13 14 15 16 17 18 19 20 21 22 23 24 25 26 27 28 29 30 31 32"
      },
      {
        "url": "http://ru.rfi.fr/rossiya/20171224-navalnogo-vydvinuli-v-prezidenty-initsiativnye-gruppy",
        "plagiat": 100,
        "words": "0 1 2 3 4 5 6 7 8 9 10 11 12 13 14 15 16 17 18 19 20 21 22 23 24 25 26 27 28 29 30 31 32"
      },
      {
        "url": "http://www.tarelka.biz/news/sobchak-na-vyborax-idealnyj-sopernik-dlya-putina-glavnye-novosti-segodnya-24-12-2017-g",
        "plagiat": 100,
        "words": "0 1 2 3 4 5 6 7 8 9 10 11 12 13 14 15 16 17 18 19 20 21 22 23 24 25 26 27 28 29 30 31 32"
      },
      {
        "url": "https://telegraf.by/2017/12/377435-navalnogo-vidvinuli-v-prezidenti-rossii",
        "plagiat": 100,
        "words": "0 1 2 3 4 5 6 7 8 9 10 11 12 13 14 15 16 17 18 19 20 21 22 23 24 25 26 27 28 29 30 31 32"
      },
      {
        "url": "http://eizvestia.com/?p=4663482&_escaped_fragment_=",
        "plagiat": 100,
        "words": "0 1 2 3 4 5 6 7 8 9 10 11 12 13 14 15 16 17 18 19 20 21 22 23 24 25 26 27 28 29 30 31 32"
      },
      {
        "url": "https://ukrbiz.net/news/59061-navalnogo-vydvinuli-v-prezidenty-rossii.html",
        "plagiat": 100,
        "words": "0 1 2 3 4 5 6 7 8 9 10 11 12 13 14 15 16 17 18 19 20 21 22 23 24 25 26 27 28 29 30 31 32"
      },
      {
        "url": "http://fakty.ua/253316-alekseya-navalnogo-vydvinuli-v-prezidenty",
        "plagiat": 100,
        "words": "0 1 2 3 4 5 6 7 8 9 10 11 12 13 14 15 16 17 18 19 20 21 22 23 24 25 26 27 28 29 30 31 32"
      },
      {
        "url": "https://ru.oxu.az/world/235531",
        "plagiat": 100,
        "words": "0 1 2 3 4 5 6 7 8 9 10 11 12 13 14 15 16 17 18 19 20 21 22 23 24 25 26 27 28 29 30 31 32"
      },
      {
        "url": "http://vnews.agency/news/society/74621-v-rf-aktivisty-vydvigayut-navalnogo-v-prezidenty.html",
        "plagiat": 100,
        "words": "0 1 2 3 4 5 6 7 8 9 10 11 12 13 14 15 16 17 18 19 20 21 22 23 24 25 26 27 28 29 30 31 32"
      },
      {
        "url": "http://news.bigmir.net/world/1130092-Navalnogo-vidvinyli-v-prezidenti-Rossii",
        "plagiat": 100,
        "words": "0 1 2 3 4 5 6 7 8 9 10 11 12 13 14 15 16 17 18 19 20 21 22 23 24 25 26 27 28 29 30 31 32"
      },
      {
        "url": "http://www.mv.org.ua/news/166725-navalnogo_vydvinuli_v_prezidenty_rossii.html",
        "plagiat": 100,
        "words": "0 1 2 3 4 5 6 7 8 9 10 11 12 13 14 15 16 17 18 19 20 21 22 23 24 25 26 27 28 29 30 31 32"
      },
      {
        "url": "https://www.novayagazeta.ru/news/2017/12/24/138185-v-moskve-initsiativnaya-gruppa-vydvinula-navalnogo-v-prezidenty",
        "plagiat": 98,
        "words": "0 1 2 3 4 5 6 7 8 9 10 11 13 14 15 16 17 18 19 20 21 22 23 24 25 26 27 28 29 30 31 32"
      },
      {
        "url": "http://maxpark.com/community/4765/content/6136154",
        "plagiat": 98,
        "words": "0 1 2 3 4 5 6 7 8 9 10 11 13 14 15 16 17 18 19 20 21 22 23 24 25 26 27 28 29 30 31 32"
      },
      {
        "url": "http://replyua.net/putin/84226-navalnyy-o-prezidentskih-vyborah-v-rf-my-gotovy-i-my-vyigraem-eti-vybory.html",
        "plagiat": 82,
        "words": "0 1 2 3 4 5 6 7 8 9 10 12 13 14 15 16 18 19 21 22 24 25 26 27 28 29 30 31 32"
      }
    ],
    "clear_text": "Невозможно признать кампанию на которую не допущен реальный кандидат Мы не признаем эти выборы но мы не устранимся Мы будем вести кампанию в стране чтобы как можно больше людей эту кампанию не признали",
    "mixed_words": ""
  },
  "spell_check": [],
  "seo_check": {
    "count_chars_with_space": "207",
    "count_chars_without_space": "175",
    "count_words": "33",
    "water_percent": "30",
    "spam_percent": "39",
    "mixed_words": [],
    "list_keys": [
      {
        "key_title": "кампанию",
        "count": "3"
      },
      {
        "key_title": "признать",
        "count": "3"
      },
      {
        "key_title": "кампанию не признали",
        "count": "2"
      }
    ],
    "list_keys_group": [
      {
        "key_title": "кампанию не признали",
        "count": "2",
        "sub_keys": [
          {
            "key_title": "кампанию",
            "count": "3"
          },
          {
            "key_title": "признать",
            "count": "3"
          }
        ]
      },
      {
        "key_title": "кампанию",
        "count": "3",
        "sub_keys": []
      },
      {
        "key_title": "признать",
        "count": "3",
        "sub_keys": []
      }
    ]
  },
  "error_code": null,
  "error_desc": null,
  "queuetext": null,
  "queueproc": null
}